setup.cfg
setup.py
yadtbroadcast_client.egg-info/PKG-INFO
yadtbroadcast_client.egg-info/SOURCES.txt
yadtbroadcast_client.egg-info/dependency_links.txt
yadtbroadcast_client.egg-info/requires.txt
yadtbroadcast_client.egg-info/top_level.txt
yadtbroadcast_client.egg-info/zip-safe
yadtbroadcastclient/__init__.py