Metadata-Version: 1.1
Name: yadtbroadcast-client
Version: 1.2.0
Summary: YADT - an Augmented Deployment Tool - The Broadcast Client Part
Home-page: http://github.com/yadt/yadtbroadcast-client
Author: Arne Hilmann, Maximilien Riehl, Marcel Wolf
Author-email: arne.hilmann@gmail.com, max@riehl.io, marcel.wolf@immobilienscout24.de
License: GNU GPL v3
Platform: UNKNOWN
Classifier: Development Status :: 4 - Beta
Classifier: Environment :: Console
Classifier: Intended Audience :: Developers
Classifier: Intended Audience :: System Administrators
Classifier: License :: OSI Approved :: GNU General Public License (GPL)
Classifier: Programming Language :: Python
Classifier: Topic :: System :: Networking
Classifier: Topic :: System :: Software Distribution
Classifier: Topic :: System :: Systems Administration
